[
  { "id": 1, "quote": "La vida no es esperar a que pase la tormenta, es aprender a bailar bajo la lluvia", "author": "Vivian Greene", "category": "motivacion" },
  { "id": 2, "quote": "El exito no es la clave de la felicidad. La felicidad es la clave del exito", "author": "Albert Schweitzer", "category": "felicidad" },
  { "id": 3, "quote": "Cree en ti mismo y en todo lo que eres. Hay algo dentro de ti que es mas grande que cualquier obstaculo", "author": "Christian D. Larson", "category": "autoestima" },
  { "id": 4, "quote": "No importa lo lento que vayas, siempre y cuando no te detengas", "author": "Confucio", "category": "perseverancia" },
  { "id": 5, "quote": "El unico modo de hacer un gran trabajo es amar lo que haces", "author": "Steve Jobs", "category": "motivacion" },
  { "id": 6, "quote": "La gratitud convierte lo que tenemos en suficiente", "author": "Esopo", "category": "gratitud" },
  { "id": 7, "quote": "No puedes detener las olas, pero puedes aprender a surfear", "author": "Jon Kabat-Zinn", "category": "superacion" },
  { "id": 8, "quote": "La mente es todo. En lo que pienses, te convertirás", "author": "Buda", "category": "mindfulness" },
  { "id": 9, "quote": "El viaje mas importante que puedes emprender es el viaje hacia ti mismo", "author": "Anonimo", "category": "crecimiento" },
  { "id": 10, "quote": "La felicidad no es algo hecho, viene de tus propias acciones", "author": "Dalai Lama", "category": "felicidad" },
  { "id": 11, "quote": "Lo que piensas, te conviertes. Lo que sientes, te atrae. Lo que imaginas, lo creas", "author": "Buda", "category": "crecimiento" },
  { "id": 12, "quote": "La paciencia es amarga, pero su fruto es dulce", "author": "Aristoteles", "category": "perseverancia" },
  { "id": 13, "quote": "No hay viento favorable para el que no sabe a donde va", "author": "Seneca", "category": "motivacion" },
  { "id": 14, "quote": "El optimismo es la fe que conduce al logro", "author": "Helen Keller", "category": "optimismo" },
  { "id": 15, "quote": "La mejor manera de predecir el futuro es crearlo", "author": "Peter Drucker", "category": "motivacion" },
  { "id": 16, "quote": "Se el cambio que quieres ver en el mundo", "author": "Mahatma Gandhi", "category": "superacion" },
  { "id": 17, "quote": "La vida es muy simple, pero insistimos en hacerla complicada", "author": "Confucio", "category": "mindfulness" },
  { "id": 18, "quote": "El que tiene un porque para vivir puede soportar casi cualquier como", "author": "Friedrich Nietzsche", "category": "superacion" },
  { "id": 19, "quote": "No cuentes los dias, haz que los dias cuenten", "author": "Muhammad Ali", "category": "motivacion" },
  { "id": 20, "quote": "La unica persona a la que debes superar eres tu mismo", "author": "Anonimo", "category": "autoestima" },
  { "id": 21, "quote": "Las dificultades preparan a personas comunes para destinos extraordinarios", "author": "C.S. Lewis", "category": "superacion" },
  { "id": 22, "quote": "La felicidad no es tener lo que quieres, sino querer lo que tienes", "author": "Anonimo", "category": "gratitud" },
  { "id": 23, "quote": "Todo lo que podemos hacer es lo mejor que podemos", "author": "Desmond Tutu", "category": "autoestima" },
  { "id": 24, "quote": "La vida es lo que pasa mientras estas ocupado haciendo otros planes", "author": "John Lennon", "category": "mindfulness" },
  { "id": 25, "quote": "El secreto de la existencia humana no solo esta en vivir, sino en saber para que se vive", "author": "Fiodor Dostoyevski", "category": "crecimiento" },
  { "id": 26, "quote": "La verdadera riqueza es la riqueza del alma", "author": "Anonimo", "category": "bienestar" },
  { "id": 27, "quote": "No juzgues cada dia por la cosecha que recoges, sino por las semillas que plantas", "author": "Robert Louis Stevenson", "category": "perseverancia" },
  { "id": 28, "quote": "Lo esencial es invisible a los ojos", "author": "Antoine de Saint-Exupery", "category": "reflexion" },
  { "id": 29, "quote": "La vida es hermosa si sabes como vivirla", "author": "Democrito", "category": "felicidad" },
  { "id": 30, "quote": "El mayor descubrimiento de mi generacion es que los seres humanos pueden alterar su vida alterando sus actitudes mentales", "author": "William James", "category": "autoestima" },
  { "id": 31, "quote": "La felicidad suele llegar a quienes estan demasiado ocupados buscando otras cosas", "author": "Anonimo", "category": "felicidad" },
  { "id": 32, "quote": "Todo tiene belleza, pero no todos pueden verla", "author": "Confucio", "category": "reflexion" },
  { "id": 33, "quote": "Lo importante no es lo que miras, sino lo que ves", "author": "Henry David Thoreau", "category": "mindfulness" },
  { "id": 34, "quote": "La vida es una aventura atrevida o no es nada", "author": "Helen Keller", "category": "motivacion" },
  { "id": 35, "quote": "El exito es ir de fracaso en fracaso sin perder el entusiasmo", "author": "Winston Churchill", "category": "perseverancia" },
  { "id": 36, "quote": "No esperes el momento perfecto, toma el momento y hazlo perfecto", "author": "Anonimo", "category": "motivacion" },
  { "id": 37, "quote": "La vida no es medida por las veces que respiras, sino por los momentos que te dejan sin aliento", "author": "Anonimo", "category": "felicidad" },
  { "id": 38, "quote": "El conocimiento habla, pero la sabiduria escucha", "author": "Jimi Hendrix", "category": "reflexion" },
  { "id": 39, "quote": "La imaginacion es mas importante que el conocimiento", "author": "Albert Einstein", "category": "creatividad" },
  { "id": 40, "quote": "La unica manera de hacer un gran trabajo es amar lo que haces", "author": "Steve Jobs", "category": "motivacion" },
  { "id": 41, "quote": "No hay nada imposible, porque los suenos de ayer son las esperanzas de hoy y pueden convertirse en realidad mañana", "author": "Anonimo", "category": "optimismo" },
  { "id": 42, "quote": "La verdadera sabiduria esta en reconocer la propia ignorancia", "author": "Socrates", "category": "reflexion" },
  { "id": 43, "quote": "El proposito de nuestra vida es ser felices", "author": "Dalai Lama", "category": "felicidad" },
  { "id": 44, "quote": "Siempre parece imposible hasta que se hace", "author": "Nelson Mandela", "category": "superacion" },
  { "id": 45, "quote": "El miedo es solo una ilusion. No tiene poder sobre ti a menos que se lo des", "author": "Anonimo", "category": "superacion" },
  { "id": 46, "quote": "La autocompasion es el camino hacia la verdadera fortaleza", "author": "Kristin Neff", "category": "autoestima" },
  { "id": 47, "quote": "No puedes cambiar el viento, pero puedes ajustar las velas", "author": "Anonimo", "category": "superacion" },
  { "id": 48, "quote": "La vida te ha dado la oportunidad de empezar de nuevo", "author": "Anonimo", "category": "renovacion" },
  { "id": 49, "quote": "La esperanza es el sueno del hombre despierto", "author": "Aristoteles", "category": "optimismo" },
  { "id": 50, "quote": "El que no arriesga no gana", "author": "Proverbio espanol", "category": "motivacion" },
  { "id": 51, "quote": "La paz viene de adentro. No la busques afuera", "author": "Buda", "category": "mindfulness" },
  { "id": 52, "quote": "La fuerza no viene de la capacidad fisica, sino de la voluntad indomable", "author": "Mahatma Gandhi", "category": "perseverancia" },
  { "id": 53, "quote": "A veces la cosa mas productiva que puedes hacer es relajarte", "author": "Mark Black", "category": "bienestar" },
  { "id": 54, "quote": "No dejes que lo que no puedes hacer interfiera con lo que si puedes hacer", "author": "John Wooden", "category": "motivacion" },
  { "id": 55, "quote": "La felicidad no es una estacion a la que llegas, sino una forma de viajar", "author": "Margaret Lee Runbeck", "category": "felicidad" },
  { "id": 56, "quote": "Todo lo que necesitas esta dentro de ti", "author": "Anonimo", "category": "autoestima" },
  { "id": 57, "quote": "El cambio es ley de vida. Y aquellos que solo miran al pasado o al presente, se perderan el futuro", "author": "John F. Kennedy", "category": "crecimiento" },
  { "id": 58, "quote": "El amor es la fuerza mas poderosa del universo", "author": "Anonimo", "category": "amor" },
  { "id": 59, "quote": "Nunca eres demasiado viejo para tener un nuevo sueno", "author": "C.S. Lewis", "category": "motivacion" },
  { "id": 60, "quote": "La vida es un 10% lo que me pasa y un 90% como reacciono a ello", "author": "Charles R. Swindoll", "category": "actitud" },
  { "id": 61, "quote": "Agradece lo que tienes y deja de quejarte. Todo tiene un proposito", "author": "Anonimo", "category": "gratitud" },
  { "id": 62, "quote": "El secreto de la felicidad es encontrar la alegria en las pequenas cosas", "author": "Anonimo", "category": "felicidad" },
  { "id": 63, "quote": "Cuida tus pensamientos, porque se convertiran en tus palabras. Cuida tus palabras, porque se convertiran en tus actos", "author": "Mahatma Gandhi", "category": "mindfulness" },
  { "id": 64, "quote": "El verdadero viaje del descubrimiento no consiste en buscar nuevos paisajes, sino en tener nuevos ojos", "author": "Marcel Proust", "category": "crecimiento" },
  { "id": 65, "quote": "La excelencia no es un acto, es un habito", "author": "Aristoteles", "category": "perseverancia" },
  { "id": 66, "quote": "Tu mismo, como cualquier otra persona, mereces tu amor y afecto", "author": "Buda", "category": "autoestima" },
  { "id": 67, "quote": "El exito no es definitivo, el fracaso no es fatal: lo que cuenta es el coraje para continuar", "author": "Winston Churchill", "category": "perseverancia" },
  { "id": 68, "quote": "No te ahogas al caer al agua, sino al quedarte sumergido", "author": "Anonimo", "category": "superacion" },
  { "id": 69, "quote": "La mente es un jardin. Cada pensamiento es una semilla", "author": "Anonimo", "category": "mindfulness" },
  { "id": 70, "quote": "La vida es demasiado corta para despertarte por la manana con arrepentimientos", "author": "Anonimo", "category": "motivacion" },
  { "id": 71, "quote": "La verdadera felicidad no se alcanza a traves de la autogratificacion, sino a traves de la fidelidad a un proposito valioso", "author": "Helen Keller", "category": "proposito" },
  { "id": 72, "quote": "La belleza de un ser humano esta en su capacidad de levantarse despues de caer", "author": "Anonimo", "category": "superacion" },
  { "id": 73, "quote": "No hay medicina que cure lo que no cura la felicidad", "author": "Gabriel Garcia Marquez", "category": "felicidad" },
  { "id": 74, "quote": "La bondad es el lenguaje que los sordos pueden oir y los ciegos pueden ver", "author": "Mark Twain", "category": "bondad" },
  { "id": 75, "quote": "La felicidad es interior, no exterior. Por eso no depende de lo que tenemos, sino de lo que somos", "author": "Anonimo", "category": "felicidad" },
  { "id": 76, "quote": "El primer paso hacia el cambio es la conciencia. El segundo paso es la aceptacion", "author": "Nathaniel Branden", "category": "crecimiento" },
  { "id": 77, "quote": "Si quieres cambiar el mundo, cambiate a ti mismo", "author": "Mahatma Gandhi", "category": "superacion" },
  { "id": 78, "quote": "La humildad no es pensar menos de ti mismo, sino pensar en ti mismo menos", "author": "C.S. Lewis", "category": "reflexion" },
  { "id": 79, "quote": "Lo que hoy parece un sacrificio, mañana sera tu mayor recompensa", "author": "Anonimo", "category": "perseverancia" },
  { "id": 80, "quote": "El tiempo es demasiado lento para quienes esperan, demasiado rapido para quienes temen", "author": "Henry Van Dyke", "category": "reflexion" },
  { "id": 81, "quote": "No puedes tener una vida positiva con una mente negativa", "author": "Anonimo", "category": "actitud" },
  { "id": 82, "quote": "La mejor forma de predecir tu futuro es crearlo", "author": "Abraham Lincoln", "category": "motivacion" },
  { "id": 83, "quote": "Las estrellas no pueden brillar sin oscuridad", "author": "Anonimo", "category": "superacion" },
  { "id": 84, "quote": "La mayor gloria no es nunca caer, sino levantarse siempre despues de caer", "author": "Confucio", "category": "perseverancia" },
  { "id": 85, "quote": "Todo sueno comienza con un sonador. Recuerda que tienes dentro de ti la fuerza, la paciencia y la pasion para alcanzar las estrellas", "author": "Harriet Tubman", "category": "motivacion" },
  { "id": 86, "quote": "La paz no es algo que deseas, es algo que creas, algo que haces, algo que eres y algo que regalas", "author": "Robert Fulghum", "category": "mindfulness" },
  { "id": 87, "quote": "Donde reina el amor, sobran las leyes", "author": "Platon", "category": "amor" },
  { "id": 88, "quote": "El alma nunca piensa sin una imagen", "author": "Aristoteles", "category": "reflexion" },
  { "id": 89, "quote": "Ama la vida que tienes mientras creas la vida que deseas", "author": "Anonimo", "category": "motivacion" },
  { "id": 90, "quote": "No importa cuantas veces caigas, sino cuantas veces te levantes", "author": "Vince Lombardi", "category": "perseverancia" },
  { "id": 91, "quote": "La mayor aventura que puedes emprender es vivir la vida de tus suenos", "author": "Oprah Winfrey", "category": "motivacion" },
  { "id": 92, "quote": "Ser feliz no significa que todo sea perfecto. Significa que has decidido ver mas alla de las imperfecciones", "author": "Anonimo", "category": "felicidad" },
  { "id": 93, "quote": "Todo lo que siempre has querido esta al otro lado del miedo", "author": "George Addair", "category": "superacion" },
  { "id": 94, "quote": "La vida es un eco: lo que envias, regresa", "author": "Anonimo", "category": "reflexion" },
  { "id": 95, "quote": "No hay camino hacia la paz, la paz es el camino", "author": "Mahatma Gandhi", "category": "mindfulness" },
  { "id": 96, "quote": "La vida no es una carrera, es un viaje para saborear cada paso", "author": "Anonimo", "category": "mindfulness" },
  { "id": 97, "quote": "Cada dia es una nueva oportunidad para cambiar tu vida", "author": "Anonimo", "category": "renovacion" },
  { "id": 98, "quote": "La unica persona que esta destinada a ser tu eres tu mismo", "author": "Anonimo", "category": "autoestima" },
  { "id": 99, "quote": "El exito y la felicidad no son un destino, son un viaje", "author": "Anonimo", "category": "bienestar" },
  { "id": 100, "quote": "Confia en ti mismo. Sabes mas de lo que crees", "author": "Benjamin Spock", "category": "autoestima" },
  { "id": 101, "quote": "La vida no tiene control remoto. Levantate y cambiala tu mismo", "author": "Anonimo", "category": "motivacion" },
  { "id": 102, "quote": "El valor no es la ausencia de miedo, sino la capacidad de seguir adelante a pesar del miedo", "author": "Anonimo", "category": "superacion" },
  { "id": 103, "quote": "La actitud es una pequena cosa que marca una gran diferencia", "author": "Winston Churchill", "category": "actitud" },
  { "id": 104, "quote": "Nuestra mayor debilidad radica en rendirnos. La forma mas segura de tener exito es intentarlo una vez mas", "author": "Thomas A. Edison", "category": "perseverancia" },
  { "id": 105, "quote": "El que mira hacia afuera, suena. El que mira hacia adentro, despierta", "author": "Carl Jung", "category": "crecimiento" },
  { "id": 106, "quote": "La felicidad compartida se multiplica, la tristeza compartida se divide", "author": "Anonimo", "category": "gratitud" },
  { "id": 107, "quote": "No es la montaña lo que desafiamos, sino lo que hay dentro de nosotros", "author": "Anonimo", "category": "superacion" },
  { "id": 108, "quote": "La musica es el lenguaje del alma", "author": "Anonimo", "category": "bienestar" },
  { "id": 109, "quote": "El silencio es a veces la mejor respuesta", "author": "Dalai Lama", "category": "mindfulness" },
  { "id": 110, "quote": "Sonrie, mañana sera otro dia", "author": "Anonimo", "category": "optimismo" },
  { "id": 111, "quote": "Lo que obtienes al alcanzar tus metas no es tan importante como lo que te conviertes al alcanzarlas", "author": "Zig Ziglar", "category": "crecimiento" },
  { "id": 112, "quote": "No hay limite para lo que puedes lograr si no te importa quien se lleva el credito", "author": "Anonimo", "category": "motivacion" },
  { "id": 113, "quote": "Si puedes sonarlo, puedes lograrlo", "author": "Walt Disney", "category": "motivacion" },
  { "id": 114, "quote": "La verdadera belleza de una persona esta en su corazon", "author": "Anonimo", "category": "bondad" },
  { "id": 115, "quote": "El perdon es la clave de la libertad interior", "author": "Anonimo", "category": "crecimiento" },
  { "id": 116, "quote": "Aprende del ayer, vive el hoy, espera el mañana. Lo importante es no dejar de preguntarse", "author": "Albert Einstein", "category": "crecimiento" },
  { "id": 117, "quote": "La mejor venganza es la felicidad", "author": "Anonimo", "category": "felicidad" },
  { "id": 118, "quote": "La paciencia tiene mas poder que la fuerza", "author": "Plutarco", "category": "perseverancia" },
  { "id": 119, "quote": "Haz de cada dia tu obra maestra", "author": "John Wooden", "category": "motivacion" },
  { "id": 120, "quote": "El secreto para salir adelante es comenzar", "author": "Mark Twain", "category": "motivacion" },
  { "id": 121, "quote": "No existe la suerte. La suerte es cuando la preparacion se encuentra con la oportunidad", "author": "Seneca", "category": "perseverancia" },
  { "id": 122, "quote": "La sonrisa cuesta menos que la electricidad y da mas luz", "author": "Proverbio escoces", "category": "felicidad" },
  { "id": 123, "quote": "Lo que no te mata te hace mas fuerte", "author": "Friedrich Nietzsche", "category": "superacion" },
  { "id": 124, "quote": "Hoy es un buen dia para tener un buen dia", "author": "Anonimo", "category": "optimismo" },
  { "id": 125, "quote": "La inteligencia consiste no solo en el conocimiento, sino tambien en la destreza de aplicar los conocimientos en la practica", "author": "Aristoteles", "category": "crecimiento" },
  { "id": 126, "quote": "Todo lo que puedes imaginar es real", "author": "Pablo Picasso", "category": "creatividad" },
  { "id": 127, "quote": "La felicidad es una mariposa que, cuando la persigues, siempre esta fuera de tu alcance, pero si te sientas en silencio, puede posarse sobre ti", "author": "Nathaniel Hawthorne", "category": "felicidad" },
  { "id": 128, "quote": "El verdadero heroismo esta en hacer lo que hay que hacer en el momento en que hay que hacerlo", "author": "Anonimo", "category": "superacion" },
  { "id": 129, "quote": "No es la especie mas fuerte la que sobrevive, ni la mas inteligente, sino la que mejor se adapta al cambio", "author": "Charles Darwin", "category": "crecimiento" },
  { "id": 130, "quote": "La vida comienza al final de tu zona de confort", "author": "Neale Donald Walsch", "category": "motivacion" },
  { "id": 131, "quote": "La gratitud es la memoria del corazon", "author": "Lao Tse", "category": "gratitud" },
  { "id": 132, "quote": "El corazon tiene razones que la razon desconoce", "author": "Blaise Pascal", "category": "reflexion" },
  { "id": 133, "quote": "No hay nada permanente excepto el cambio", "author": "Heraclito", "category": "crecimiento" },
  { "id": 134, "quote": "El que tiene un jardin y una biblioteca, tiene todo lo que necesita", "author": "Ciceron", "category": "bienestar" },
  { "id": 135, "quote": "La vida es demasiado importante como para tomarsela en serio", "author": "Oscar Wilde", "category": "felicidad" },
  { "id": 136, "quote": "La creatividad es la inteligencia divirtiendose", "author": "Albert Einstein", "category": "creatividad" },
  { "id": 137, "quote": "Uno no descubre nuevos horizontes si no tiene el valor de perder de vista la costa", "author": "Anonimo", "category": "motivacion" },
  { "id": 138, "quote": "El mejor regalo que puedes dar a los demas es tu presencia", "author": "Anonimo", "category": "mindfulness" },
  { "id": 139, "quote": "La esperanza es el faro que ilumina el camino en la oscuridad", "author": "Anonimo", "category": "optimismo" },
  { "id": 140, "quote": "El amor es la unica fuerza capaz de transformar un enemigo en amigo", "author": "Martin Luther King Jr.", "category": "amor" },
  { "id": 141, "quote": "La verdad os hara libres", "author": "Jesus de Nazaret", "category": "reflexion" },
  { "id": 142, "quote": "Cada persona es un mundo. Y cada mundo merece respeto", "author": "Anonimo", "category": "bondad" },
  { "id": 143, "quote": "La mayoria de las personas son tan felices como deciden serlo", "author": "Abraham Lincoln", "category": "actitud" },
  { "id": 144, "quote": "El que pregunta es tonto por cinco minutos. El que no pregunta es tonto para siempre", "author": "Proverbio chino", "category": "aprendizaje" },
  { "id": 145, "quote": "Haz el bien sin mirar a quien", "author": "Refran popular", "category": "bondad" },
  { "id": 146, "quote": "La felicidad es una eleccion, no una consecuencia", "author": "Anonimo", "category": "felicidad" },
  { "id": 147, "quote": "Nada es para siempre, ni siquiera los problemas", "author": "Anonimo", "category": "optimismo" },
  { "id": 148, "quote": "El cambio es dificil al principio, caotico en el medio y hermoso al final", "author": "Robin Sharma", "category": "crecimiento" },
  { "id": 149, "quote": "No te tomes la vida demasiado en serio, nunca saldras vivo de ella", "author": "Elbert Hubbard", "category": "felicidad" },
  { "id": 150, "quote": "La mejor herencia de los padres es una buena educacion", "author": "Anonimo", "category": "aprendizaje" },
  { "id": 151, "quote": "El amor no es mirarse el uno al otro, sino mirar juntos en la misma direccion", "author": "Antoine de Saint-Exupery", "category": "amor" },
  { "id": 152, "quote": "La verdadera fortaleza no esta en nunca caer, sino en levantarse cada vez que caemos", "author": "Anonimo", "category": "perseverancia" },
  { "id": 153, "quote": "La vida es un libro abierto. Cada dia es una pagina nueva", "author": "Anonimo", "category": "renovacion" },
  { "id": 154, "quote": "Da siempre lo mejor de ti. Lo que plantes ahora, lo cosecharas despues", "author": "Og Mandino", "category": "perseverancia" },
  { "id": 155, "quote": "El exito es la suma de pequenos esfuerzos repetidos dia tras dia", "author": "Robert Collier", "category": "perseverancia" },
  { "id": 156, "quote": "La belleza esta en los ojos del que mira", "author": "Oscar Wilde", "category": "reflexion" },
  { "id": 157, "quote": "La soledad es la suerte de un alma que se reconoce a si misma", "author": "Anonimo", "category": "reflexion" },
  { "id": 158, "quote": "El tiempo es el mejor autor: siempre encuentra un final perfecto", "author": "Anonimo", "category": "reflexion" },
  { "id": 159, "quote": "La felicidad no es un destino, es una forma de vida", "author": "Anonimo", "category": "felicidad" },
  { "id": 160, "quote": "No hay atajos para llegar a lugares que valen la pena", "author": "Beverly Sills", "category": "perseverancia" },
  { "id": 161, "quote": "Cree en tus suenos y ellos te llevaran lejos", "author": "Anonimo", "category": "motivacion" },
  { "id": 162, "quote": "El silencio es el grito mas fuerte", "author": "Anonimo", "category": "reflexion" },
  { "id": 163, "quote": "Quien siembra vientos, recoge tempestades. Quien siembra amor, recoge paz", "author": "Anonimo", "category": "bondad" },
  { "id": 164, "quote": "La autenticidad es la practica diaria de dejar ir lo que creemos que deberiamos ser y abrazar lo que somos", "author": "Brene Brown", "category": "autoestima" },
  { "id": 165, "quote": "El perdon no cambia el pasado, pero amplia el futuro", "author": "Anonimo", "category": "crecimiento" },
  { "id": 166, "quote": "La mente es como un paracaidas: solo funciona si se abre", "author": "Albert Einstein", "category": "aprendizaje" },
  { "id": 167, "quote": "Para viajar lejos no hay mejor nave que un libro", "author": "Emily Dickinson", "category": "aprendizaje" },
  { "id": 168, "quote": "La noche es mas oscura justo antes del amanecer", "author": "Proverbio", "category": "optimismo" },
  { "id": 169, "quote": "Tus pensamientos son la causa de tu realidad", "author": "Anonimo", "category": "mindfulness" },
  { "id": 170, "quote": "La felicidad no es tener lo que quieres, es amar lo que tienes", "author": "Anonimo", "category": "gratitud" },
  { "id": 171, "quote": "El optimismo perpetuo es una fuerza multiplicadora", "author": "Colin Powell", "category": "optimismo" },
  { "id": 172, "quote": "No dejes que el ruido de las opiniones ajenas acalle tu voz interior", "author": "Steve Jobs", "category": "autoestima" },
  { "id": 173, "quote": "La vida es una flor de la que el amor es la miel", "author": "Victor Hugo", "category": "amor" },
  { "id": 174, "quote": "El sabio no dice todo lo que piensa, pero siempre piensa todo lo que dice", "author": "Aristoteles", "category": "reflexion" },
  { "id": 175, "quote": "La paciencia es el arte de esperar sin sufrir", "author": "Anonimo", "category": "bienestar" },
  { "id": 176, "quote": "Todo gran viaje comienza con un primer paso", "author": "Lao Tse", "category": "motivacion" },
  { "id": 177, "quote": "El amor y la compasion son necesidades, no lujos. Sin ellos la humanidad no puede sobrevivir", "author": "Dalai Lama", "category": "amor" },
  { "id": 178, "quote": "La educacion es el arma mas poderosa para cambiar el mundo", "author": "Nelson Mandela", "category": "aprendizaje" },
  { "id": 179, "quote": "La coherencia es la clave del exito", "author": "Anonimo", "category": "perseverancia" },
  { "id": 180, "quote": "El verdadero viaje del descubrimiento no es buscar nuevos paisajes, sino ver con nuevos ojos", "author": "Marcel Proust", "category": "crecimiento" },
  { "id": 181, "quote": "No cuentes lo que has hecho, muestra lo que puedes hacer", "author": "Anonimo", "category": "motivacion" },
  { "id": 182, "quote": "La unica persona que puede limitarte eres tu mismo", "author": "Anonimo", "category": "autoestima" },
  { "id": 183, "quote": "La verdadera sabiduria esta en saber que no sabemos nada", "author": "Socrates", "category": "aprendizaje" },
  { "id": 184, "quote": "El exito es aprender a ir de fracaso en fracaso sin desesperarse", "author": "Winston Churchill", "category": "perseverancia" },
  { "id": 185, "quote": "La vida es demasiado corta para beber mal vino", "author": "Proverbio aleman", "category": "felicidad" },
  { "id": 186, "quote": "Cada dia es una nueva oportunidad. Aprovechala", "author": "Anonimo", "category": "motivacion" },
  { "id": 187, "quote": "La belleza del ser humano esta en su capacidad de reinventarse", "author": "Anonimo", "category": "renovacion" },
  { "id": 188, "quote": "El conocimiento es poder, pero la sabiduria es libertad", "author": "Anonimo", "category": "aprendizaje" },
  { "id": 189, "quote": "La musica es el refugio del alma cansada", "author": "Anonimo", "category": "bienestar" },
  { "id": 190, "quote": "No hay mal que dure cien anos ni cuerpo que lo resista", "author": "Refran popular", "category": "optimismo" },
  { "id": 191, "quote": "El amor es la respuesta, pase cual sea la pregunta", "author": "Anonimo", "category": "amor" },
  { "id": 192, "quote": "La naturaleza es el mejor lugar para encontrar paz interior", "author": "Anonimo", "category": "bienestar" },
  { "id": 193, "quote": "La sonrisa es la curva mas bella del cuerpo humano", "author": "Anonimo", "category": "felicidad" },
  { "id": 194, "quote": "La verdadera paz mental viene de no preocuparse por el pasado ni el futuro", "author": "Anonimo", "category": "mindfulness" },
  { "id": 195, "quote": "Cada persona que pasa por tu vida tiene un proposito. Aprende de ellos", "author": "Anonimo", "category": "crecimiento" },
  { "id": 196, "quote": "La vida es el arte del encuentro", "author": "Anonimo", "category": "amor" },
  { "id": 197, "quote": "La honestidad es el primer capitulo del libro de la sabiduria", "author": "Thomas Jefferson", "category": "reflexion" },
  { "id": 198, "quote": "Haz lo que puedas, con lo que tengas, donde estes", "author": "Theodore Roosevelt", "category": "motivacion" },
  { "id": 199, "quote": "La vida es como andar en bicicleta: para mantener el equilibrio debes seguir moviendote", "author": "Albert Einstein", "category": "perseverancia" },
  { "id": 200, "quote": "La felicidad se encuentra cuando dejas de buscar y comienzas a vivir", "author": "Anonimo", "category": "felicidad" },
  { "id": 201, "quote": "El miedo es solo una ilusion. No tiene poder sobre ti", "author": "Anonimo", "category": "superacion" },
  { "id": 202, "quote": "La vida es una obra de teatro que no permite ensayos. Por eso, canta, rie, baila, ama y vive intensamente", "author": "Anonimo", "category": "motivacion" },
  { "id": 203, "quote": "El conocimiento sin accion es como un libro sin leer", "author": "Anonimo", "category": "aprendizaje" },
  { "id": 204, "quote": "La mejor manera de empezar es dejar de hablar y comenzar a hacer", "author": "Walt Disney", "category": "motivacion" },
  { "id": 205, "quote": "La verdadera riqueza es la riqueza del alma", "author": "Anonimo", "category": "bienestar" },
  { "id": 206, "quote": "El amor es la llave maestra que abre las puertas de la felicidad", "author": "Oliver Wendell Holmes", "category": "amor" },
  { "id": 207, "quote": "No esperes el permiso de nadie para ser feliz", "author": "Anonimo", "category": "felicidad" },
  { "id": 208, "quote": "La vida es un espejo: si sonries, te sonrie", "author": "Anonimo", "category": "actitud" },
  { "id": 209, "quote": "El que sabe lo que quiere, encontrara el como", "author": "Anonimo", "category": "motivacion" },
  { "id": 210, "quote": "La paciencia es la fortaleza del debil y la impaciencia la debilidad del fuerte", "author": "Immanuel Kant", "category": "perseverancia" },
  { "id": 211, "quote": "El universo no esta fuera de ti. Mirate dentro", "author": "Anonimo", "category": "crecimiento" },
  { "id": 212, "quote": "La bondad es la riqueza que nunca se agota", "author": "Anonimo", "category": "bondad" },
  { "id": 213, "quote": "La vida es el mayor de los regalos. Disfrutala", "author": "Anonimo", "category": "gratitud" },
  { "id": 214, "quote": "El secreto de la vida no es hacer lo que te gusta, sino encontrar el gusto en lo que haces", "author": "Anonimo", "category": "motivacion" },
  { "id": 215, "quote": "Cada dia es una segunda oportunidad", "author": "Anonimo", "category": "renovacion" },
  { "id": 216, "quote": "La verdadera fortaleza es reconocer las propias debilidades", "author": "Anonimo", "category": "autoestima" },
  { "id": 217, "quote": "El amor no se encuentra, se construye", "author": "Anonimo", "category": "amor" },
  { "id": 218, "quote": "La vida sin musica seria un error", "author": "Friedrich Nietzsche", "category": "bienestar" },
  { "id": 219, "quote": "El silencio es el sueno que alimenta la sabiduria", "author": "Francis Bacon", "category": "reflexion" },
  { "id": 220, "quote": "No hay nada mas fuerte que la ternura", "author": "Anonimo", "category": "bondad" },
  { "id": 221, "quote": "La felicidad es un perfume que no puedes derramar sobre los demas sin que te caigan unas gotas", "author": "Anonimo", "category": "felicidad" },
  { "id": 222, "quote": "El secreto de la sabiduria es saber escuchar", "author": "Anonimo", "category": "aprendizaje" },
  { "id": 223, "quote": "La vida es corta. Vive intensamente", "author": "Anonimo", "category": "motivacion" },
  { "id": 224, "quote": "La felicidad es la unica cosa que se multiplica cuando se comparte", "author": "Anonimo", "category": "gratitud" },
  { "id": 225, "quote": "El fracaso es la oportunidad de empezar de nuevo con mas inteligencia", "author": "Henry Ford", "category": "perseverancia" },
  { "id": 226, "quote": "La verdadera aventura esta en el interior", "author": "Anonimo", "category": "crecimiento" },
  { "id": 227, "quote": "No hay camino facil hacia la libertad", "author": "Anonimo", "category": "superacion" },
  { "id": 228, "quote": "El arte de ser sabio es el arte de saber que pasar por alto", "author": "William James", "category": "reflexion" },
  { "id": 229, "quote": "Lo mas hermoso del mundo es ver a alguien sonreir y saber que tu eres la razon", "author": "Anonimo", "category": "felicidad" },
  { "id": 230, "quote": "La musica es el latido del corazon de la vida", "author": "Anonimo", "category": "bienestar" },
  { "id": 231, "quote": "El exito consiste en obtener lo que se desea. La felicidad, en disfrutar lo que se obtiene", "author": "Anonimo", "category": "felicidad" },
  { "id": 232, "quote": "La vida es un eco. Si no te gusta lo que recibes, mira lo que estas emitiendo", "author": "Anonimo", "category": "reflexion" },
  { "id": 233, "quote": "Donde hay amor hay vida", "author": "Mahatma Gandhi", "category": "amor" },
  { "id": 234, "quote": "La vida es bella. Disfrutala con todos tus sentidos", "author": "Anonimo", "category": "bienestar" },
  { "id": 235, "quote": "El amor es el puente entre dos almas", "author": "Anonimo", "category": "amor" },
  { "id": 236, "quote": "La felicidad es interior, no exterior, por eso no depende de lo que tenemos, sino de lo que somos", "author": "Anonimo", "category": "felicidad" },
  { "id": 237, "quote": "La vida no es un problema a resolver, sino una realidad a experimentar", "author": "Soren Kierkegaard", "category": "mindfulness" },
  { "id": 238, "quote": "El que quiere hacer algo, encuentra un medio. El que no quiere hacer nada, encuentra una excusa", "author": "Proverbio arabe", "category": "motivacion" },
  { "id": 239, "quote": "La vida es un conjunto de pequenas alegrias que debemos valorar", "author": "Anonimo", "category": "gratitud" },
  { "id": 240, "quote": "No hay nada mas valioso que el tiempo presente", "author": "Anonimo", "category": "mindfulness" },
  { "id": 241, "quote": "El amor es el unico tesoro que crece cuando lo compartes", "author": "Anonimo", "category": "amor" },
  { "id": 242, "quote": "La sonrisa es el idioma universal del alma", "author": "Anonimo", "category": "felicidad" },
  { "id": 243, "quote": "La paz viene de adentro. No la busques afuera", "author": "Buda", "category": "mindfulness" },
  { "id": 244, "quote": "La musica da alma al universo, alas a la mente, vuelo a la imaginacion y vida a todo", "author": "Platon", "category": "bienestar" },
  { "id": 245, "quote": "El que tiene imaginacion, pero no tiene conocimiento, tiene alas pero no pies", "author": "Joseph Joubert", "category": "aprendizaje" },
  { "id": 246, "quote": "La vida es demasiado corta para despertarse con remordimientos", "author": "Anonimo", "category": "motivacion" },
  { "id": 247, "quote": "La felicidad es la certeza de no sentirse perdido", "author": "Anonimo", "category": "felicidad" },
  { "id": 248, "quote": "El respeto al derecho ajeno es la paz", "author": "Benito Juarez", "category": "reflexion" },
  { "id": 249, "quote": "La amistad duplica las alegrias y divide las angustias", "author": "Francis Bacon", "category": "amor" },
  { "id": 250, "quote": "No hay espectaculo mas hermoso que la mirada de un nino que lee", "author": "Anonimo", "category": "aprendizaje" },
  { "id": 251, "quote": "El bien no hace ruido y el ruido no hace bien", "author": "Refran popular", "category": "bondad" },
  { "id": 252, "quote": "El amor es la unica locura que no se cura", "author": "Anonimo", "category": "amor" },
  { "id": 253, "quote": "Ama tu projimo como a ti mismo", "author": "Jesus de Nazaret", "category": "amor" },
  { "id": 254, "quote": "La felicidad es un camino, no un destino", "author": "Anonimo", "category": "felicidad" },
  { "id": 255, "quote": "El que lee mucho y anda mucho, ve mucho y sabe mucho", "author": "Miguel de Cervantes", "category": "aprendizaje" },
  { "id": 256, "quote": "La esperanza es el combustible del alma", "author": "Anonimo", "category": "optimismo" },
  { "id": 257, "quote": "El amor verdadero no tiene final feliz. El amor verdadero simplemente no tiene final", "author": "Anonimo", "category": "amor" },
  { "id": 258, "quote": "La vida es corta pero ancha. Vívela con intensidad", "author": "Anonimo", "category": "motivacion" },
  { "id": 259, "quote": "El que no vive para servir, no sirve para vivir", "author": "Anonimo", "category": "bondad" },
  { "id": 260, "quote": "La belleza es un reflejo del alma", "author": "Anonimo", "category": "reflexion" },
  { "id": 261, "quote": "La vida es un misterio que hay que vivir, no un problema que hay que resolver", "author": "Anonimo", "category": "mindfulness" },
  { "id": 262, "quote": "El mejor espejo es un viejo amigo", "author": "Proverbio espanol", "category": "amistad" },
  { "id": 263, "quote": "No hay atajos hacia la felicidad. La felicidad es el camino", "author": "Anonimo", "category": "felicidad" },
  { "id": 264, "quote": "La amistad es el amor sin alas", "author": "Lord Byron", "category": "amistad" },
  { "id": 265, "quote": "La vida es un constante aprendizaje", "author": "Anonimo", "category": "aprendizaje" },
  { "id": 266, "quote": "El que sabe esperar, todo lo alcanza", "author": "Anonimo", "category": "perseverancia" },
  { "id": 267, "quote": "La experiencia es la madre de la ciencia", "author": "Miguel de Cervantes", "category": "aprendizaje" },
  { "id": 268, "quote": "No hay medicina que cure lo que no cura la felicidad", "author": "Anonimo", "category": "felicidad" },
  { "id": 269, "quote": "El amor es el vino de la vida", "author": "Anonimo", "category": "amor" },
  { "id": 270, "quote": "La verdadera generosidad consiste en dar antes de que te pidan", "author": "Anonimo", "category": "bondad" },
  { "id": 271, "quote": "La felicidad es la ausencia de miedo", "author": "Anonimo", "category": "felicidad" },
  { "id": 272, "quote": "El viaje mas importante es hacia el interior de uno mismo", "author": "Anonimo", "category": "crecimiento" },
  { "id": 273, "quote": "La musica es el arte mas directo, entra por el oido y va al corazon", "author": "Magdalena Martinez", "category": "bienestar" },
  { "id": 274, "quote": "La amistad es el ingrediente mas importante de la vida", "author": "Anonimo", "category": "amistad" },
  { "id": 275, "quote": "El pasado es un papel quemado. El futuro es incierto. El presente es un regalo", "author": "Anonimo", "category": "mindfulness" },
  { "id": 276, "quote": "No hay nada mas hermoso que ser amado", "author": "Anonimo", "category": "amor" },
  { "id": 277, "quote": "La vida es un suspiro entre dos eternidades", "author": "Thomas Carlyle", "category": "reflexion" },
  { "id": 278, "quote": "La felicidad es la sonrisa del alma", "author": "Anonimo", "category": "felicidad" },
  { "id": 279, "quote": "No hay que ir para atras ni para darse impulso", "author": "Lao Tse", "category": "renovacion" },
  { "id": 280, "quote": "La vida es un enigma que debemos descifrar viviendo", "author": "Anonimo", "category": "crecimiento" },
  { "id": 281, "quote": "Aprender a vivir es aprender a soltar", "author": "Anonimo", "category": "crecimiento" },
  { "id": 282, "quote": "La mejor manera de encontrar la paz es crearla dentro de ti", "author": "Anonimo", "category": "mindfulness" },
  { "id": 283, "quote": "No hay nada mas valioso que una sonrisa sincera", "author": "Anonimo", "category": "felicidad" },
  { "id": 284, "quote": "El amor es la sabiduria del tonto y la tonteria del sabio", "author": "Samuel Johnson", "category": "amor" },
  { "id": 285, "quote": "El que tiene un amigo, tiene un tesoro", "author": "Anonimo", "category": "amistad" },
  { "id": 286, "quote": "La vida es demasiado importante para tomarsela en serio", "author": "Oscar Wilde", "category": "felicidad" },
  { "id": 287, "quote": "La sabiduria comienza en la reflexion", "author": "Socrates", "category": "reflexion" },
  { "id": 288, "quote": "El amor es la luz que ilumina el camino de la vida", "author": "Anonimo", "category": "amor" },
  { "id": 289, "quote": "La vida es un viaje, no un destino", "author": "Ralph Waldo Emerson", "category": "crecimiento" },
  { "id": 290, "quote": "Todo es cuestion de actitud. La vida no espera, hay que vivirla", "author": "Anonimo", "category": "actitud" },
  { "id": 291, "quote": "El unico imposible es aquello que no intentas", "author": "Anonimo", "category": "motivacion" },
  { "id": 292, "quote": "No hay tormenta que dure cien anos, ni oscuridad que apague un amanecer", "author": "Anonimo", "category": "optimismo" },
  { "id": 293, "quote": "La paz interior no depende de las circunstancias externas", "author": "Epicteto", "category": "mindfulness" },
  { "id": 294, "quote": "El secreto de la felicidad esta en aceptar lo que no se puede cambiar y cambiar lo que se puede", "author": "Anonimo", "category": "felicidad" },
  { "id": 295, "quote": "Cada dia es un regalo. Por eso se llama presente", "author": "Anonimo", "category": "mindfulness" },
  { "id": 296, "quote": "La vida te pondra obstaculos, pero los limites los pones tu", "author": "Anonimo", "category": "superacion" },
  { "id": 297, "quote": "No esperes a que las condiciones sean perfectas para empezar. Empezar hace que las condiciones sean perfectas", "author": "Alan Cohen", "category": "motivacion" },
  { "id": 298, "quote": "El mejor momento del dia es ahora", "author": "Anonimo", "category": "mindfulness" },
  { "id": 299, "quote": "El valor de la vida no esta en su duracion sino en su contenido", "author": "Seneca", "category": "reflexion" },
  { "id": 300, "quote": "La unica forma de hacer un trabajo extraordinario es apasionarse por lo que haces", "author": "Steve Jobs", "category": "motivacion" }
]